por_que/__init__.py
por_que/__version__.py
por_que/_version.py
por_que/constants.py
por_que/enums.py
por_que/exceptions.py
por_que/file_metadata.py
por_que/pages.py
por_que/physical.py
por_que/protocols.py
por_que/parsers/__init__.py
por_que/parsers/logical_types.py
por_que/parsers/physical_types.py
por_que/parsers/page_content/__init__.py
por_que/parsers/page_content/compressors.py
por_que/parsers/page_content/data.py
por_que/parsers/page_content/dictionary.py
por_que/parsers/parquet/__init__.py
por_que/parsers/parquet/base.py
por_que/parsers/parquet/column.py
por_que/parsers/parquet/enums.py
por_que/parsers/parquet/geostats.py
por_que/parsers/parquet/keyvalue.py
por_que/parsers/parquet/metadata.py
por_que/parsers/parquet/page.py
por_que/parsers/parquet/page_index.py
por_que/parsers/parquet/row_group.py
por_que/parsers/parquet/schema.py
por_que/parsers/parquet/statistics.py
por_que/parsers/thrift/__init__.py
por_que/parsers/thrift/constants.py
por_que/parsers/thrift/enums.py
por_que/parsers/thrift/parser.py
por_que/structuring/__init__.py
por_que/structuring/factory.py
por_que/structuring/list.py
por_que/structuring/map.py
por_que/structuring/primitive.py
por_que/structuring/protocols.py
por_que/structuring/reconstruct.py
por_que/structuring/struct.py
por_que/util/__init__.py
por_que/util/async_adapter.py
por_que/util/iteration.py
por_que/util/models.py
por_que-0.2.4.dist-info/METADATA
por_que-0.2.4.dist-info/WHEEL
por_que-0.2.4.dist-info/licenses/LICENSE
por_que-0.2.4.dist-info/RECORD
