Metadata-Version: 2.4
Name: por-que
Version: 0.2.4
Summary: Pure-python parquet parser, for education
Project-URL: Repository, https://github.com/jkeifer/por-que
Author-email: Jarrett Keifer <jkeifer0@gmail.com>
License: Apache License 2.0
License-File: LICENSE
Requires-Python: >=3.13
Requires-Dist: brotli>=1.1.0
Requires-Dist: hctef[async]>=0.1.1
Requires-Dist: pydantic>=2.11.7
Requires-Dist: python-snappy>=0.6.1
Requires-Dist: zstandard>=0.23.0
Provides-Extra: lzo
Requires-Dist: python-lzo>=1.15; extra == 'lzo'
